LICENSE
MANIFEST.in
README.md
requirements.txt
setup.cfg
setup.py
src/nextgpt/__init__.py
src/nextgpt.egg-info/PKG-INFO
src/nextgpt.egg-info/SOURCES.txt
src/nextgpt.egg-info/dependency_links.txt
src/nextgpt.egg-info/requires.txt
src/nextgpt.egg-info/top_level.txt
src/nextgpt/dataset/__init__.py
src/nextgpt/dataset/prompt_dataset.py
src/nextgpt/dataset/reward_dataset.py
src/nextgpt/dataset/sft_dataset.py
src/nextgpt/dataset/utils.py
src/nextgpt/experience_maker/__init__.py
src/nextgpt/experience_maker/base.py
src/nextgpt/experience_maker/naive.py
src/nextgpt/finetuning/__init__.py
src/nextgpt/finetuning/callbacks.py
src/nextgpt/finetuning/trainer.py
src/nextgpt/models/__init__.py
src/nextgpt/models/generation.py
src/nextgpt/models/generation_utils.py
src/nextgpt/models/lora.py
src/nextgpt/models/loss.py
src/nextgpt/models/utils.py
src/nextgpt/models/base/__init__.py
src/nextgpt/models/base/actor.py
src/nextgpt/models/base/critic.py
src/nextgpt/models/base/lm.py
src/nextgpt/models/base/reward_model.py
src/nextgpt/models/bloom/__init__.py
src/nextgpt/models/bloom/bloom_actor.py
src/nextgpt/models/bloom/bloom_critic.py
src/nextgpt/models/bloom/bloom_lm.py
src/nextgpt/models/bloom/bloom_rm.py
src/nextgpt/models/gpt/__init__.py
src/nextgpt/models/gpt/gpt_actor.py
src/nextgpt/models/gpt/gpt_critic.py
src/nextgpt/models/gpt/gpt_lm.py
src/nextgpt/models/gpt/gpt_rm.py
src/nextgpt/models/opt/__init__.py
src/nextgpt/models/opt/opt_actor.py
src/nextgpt/models/opt/opt_critic.py
src/nextgpt/models/opt/opt_lm.py
src/nextgpt/models/opt/opt_rm.py
src/nextgpt/replay_buffer/__init__.py
src/nextgpt/replay_buffer/base.py
src/nextgpt/replay_buffer/naive.py
src/nextgpt/replay_buffer/utils.py
src/nextgpt/trainer/__init__.py
src/nextgpt/trainer/base.py
src/nextgpt/trainer/ppo.py
src/nextgpt/trainer/rm.py
src/nextgpt/trainer/sft.py
src/nextgpt/trainer/utils.py
src/nextgpt/trainer/callbacks/__init__.py
src/nextgpt/trainer/callbacks/base.py
src/nextgpt/trainer/callbacks/log_metrics.py
src/nextgpt/trainer/callbacks/performance_evaluator.py
src/nextgpt/trainer/callbacks/save_checkpoint.py
src/nextgpt/trainer/strategies/__init__.py
