Metadata-Version: 2.1
Name: nextgpt
Version: 0.0.4
Summary: nextGPT
Home-page: https://github.com/louiezzang/next-gpt
Author: Younggue Bae
Requires-Python: >=3.6
License-File: LICENSE
